pygnss/hatanaka.py
pygnss/time.py
pygnss/ionex.py
pygnss/nequick.py
pygnss/sinex.py
pygnss/tensorial.py
pygnss/decorator.py
pygnss/constants.py
pygnss/__init__.py
pygnss/cl.py
pygnss/_c_ext.cpython-312-darwin.so
pygnss/logger.py
pygnss/geodetic.py
pygnss/file.py
pygnss/rinex.py
pygnss/stats.py
pygnss/orbit/kepler.py
pygnss/orbit/__init__.py
pygnss/orbit/tle.py
pygnss/parsers/rtklib/stats.py
pygnss/_c_ext/src/constants.c
pygnss/_c_ext/src/mtable_init.c
pygnss/_c_ext/src/hatanaka.c
pygnss/_c_ext/src/klobuchar.c
pygnss/_c_ext/src/helpers.c
pygnss/gnss/__init__.py
pygnss/gnss/edit.py
pygnss/gnss/types.py
pygnss/gnss/residuals.py
pygnss/gnss/observables.py
pygnss/iono/gim.py
pygnss/iono/chapman.py
pygnss/iono/__init__.py
pygnss/filter/ukf.py
pygnss/filter/models.py
pygnss/filter/__init__.py
pygnss/filter/ekf.py
pygnss/filter/particle.py
pygnss-2.1.2.dist-info/RECORD
pygnss-2.1.2.dist-info/WHEEL
pygnss-2.1.2.dist-info/entry_points.txt
pygnss-2.1.2.dist-info/top_level.txt
pygnss-2.1.2.dist-info/METADATA
pygnss-2.1.2.dist-info/licenses/LICENSE
