Metadata-Version: 2.4
Name: pygnss
Version: 2.1.2
Summary: Package with utilities and tools for GNSS data processing
Author-email: Miquel Garcia-Fernandez <miquel@mgfernan.com>
License-Expression: MIT
Project-URL: Homepage, https://github.com/mgfernan/pygnss
Requires-Python: >=3.10
License-File: LICENSE
Requires-Dist: nequick>=0.2.0
Requires-Dist: numpy
Requires-Dist: pandas>=2.2
Requires-Dist: pyarrow>=18.0.0
Provides-Extra: test
Requires-Dist: pytest>=8.3.4; extra == "test"
Requires-Dist: pytest-env>=1.1.5; extra == "test"
Requires-Dist: pytest-mocha>=0.4.0; extra == "test"
Requires-Dist: flake8>=7.0.0; extra == "test"
Requires-Dist: pnt-datasets>=0.2.2; extra == "test"
Requires-Dist: package-name>=0.1; extra == "test"
Provides-Extra: release
Requires-Dist: python-semantic-release>=9.4.0; extra == "release"
Dynamic: license-file
